[
  {
    "name": "bug",
    "color": "#F66570",
    "description": "Something isn't working or went wrong"
  },
  {
    "name": "docs",
    "color": "#0075CA",
    "description": "Documentation changes or additions"
  },
  {
    "name": "duplicate",
    "color": "#CFD3D7",
    "description": "This issue or pull request already exists"
  },
  {
    "name": "feat",
    "color": "#A2EEEF",
    "description": "New feature request or implementation"
  },
  {
    "name": "fixed",
    "color": "#FFFFFF",
    "description": "This issue has been resolved"
  },
  {
    "name": "attention",
    "color": "#008672",
    "description": "Needs extra attention or discussion"
  },
  {
    "name": "question",
    "color": "#D876E3",
    "description": "Further information is requested"
  },
  {
    "name": "test",
    "color": "#0C6267",
    "description": "Testing only, not for production"
  },
  {
    "name": "refactor",
    "color": "#000000",
    "description": "Code cleanup, refactoring, or renaming"
  },
  {
    "name": "priority:0",
    "color": "#b60205",
    "description": "Critical — Immediate response required"
  },
  {
    "name": "priority:1",
    "color": "#d93f0b",
    "description": "High — Address as soon as possible"
  },
  {
    "name": "priority:2",
    "color": "#c2e0c6",
    "description": "Medium — Normal priority"
  },
  {
    "name": "priority:3",
    "color": "#c5def5",
    "description": "Low — No rush"
  },
  {
    "name": "priority:4",
    "color": "#bfd4f2",
    "description": "Backlog — Someday maybe"
  }
]
